tomaster/__init__.py
tomaster/_test.py
tomaster/tomato.py
tomaster-0.0.5.dist-info/METADATA
tomaster-0.0.5.dist-info/WHEEL
tomaster-0.0.5.dist-info/top_level.txt
tomaster-0.0.5.dist-info/RECORD
