Metadata-Version: 2.1
Name: tomaster
Version: 0.0.5
Summary: Topological Mode Analysis on Steroids
Home-page: https://github.com/louisabraham/tomaster
Author: Louis Abraham
Author-email: louis.abraham@yahoo.fr
License: MIT
Platform: UNKNOWN
Classifier: Topic :: Scientific/Engineering
Classifier: Intended Audience :: Science/Research
Requires-Dist: numpy
Requires-Dist: numba
Requires-Dist: scikit-learn
Requires-Dist: scikit-image
